hat/json/py.typed
hat/json/schema.py
hat/json/encoder.py
hat/json/convert.py
hat/json/__init__.py
hat/json/path.py
hat/json/data.py
hat/json/patch.py
hat/json/vt.py
hat/json/json_schema_repo.json
hat_json-0.6.3.dist-info/LICENSE
hat_json-0.6.3.dist-info/entry_points.txt
hat_json-0.6.3.dist-info/METADATA
hat_json-0.6.3.dist-info/WHEEL
hat_json-0.6.3.dist-info/RECORD
