Metadata-Version: 2.1
Name: hat-json
Version: 0.6.3
Summary: Hat JSON library
License: Apache-2.0
Classifier: Programming Language :: Python :: 3
Classifier: License :: OSI Approved :: Apache Software License
Provides-Extra: rs
Provides-Extra: dev
Requires-Dist: hat-util ~=0.6.19
Requires-Dist: jsonpatch ~=1.33
Requires-Dist: jsonschema ~=4.23.0
Requires-Dist: pyyaml ~=6.0.2
Requires-Dist: referencing ~=0.35.1
Requires-Dist: tomli ~=2.0.1; python_version<'3.11'
Requires-Dist: tomli_w ~=1.2.0
Requires-Dist: jsonschema_rs ~=0.29.1; extra == 'rs'
Requires-Dist: hat-doit ~=0.16.2; extra == 'dev'
Requires-Dist: sphinxcontrib-programoutput >=0.17; extra == 'dev'
Requires-Python: >=3.10
Project-URL: Homepage, http://hat-open.com
Project-URL: Repository, https://github.com/hat-open/hat-json.git
Project-URL: Documentation, http://hat-json.hat-open.com
